burdoc/__init__.py
burdoc/burdoc_parser.py
burdoc/elements/__init__.py
burdoc/elements/aside.py
burdoc/elements/bbox.py
burdoc/elements/drawing.py
burdoc/elements/element.py
burdoc/elements/font.py
burdoc/elements/image.py
burdoc/elements/line.py
burdoc/elements/section.py
burdoc/elements/span.py
burdoc/elements/table.py
burdoc/elements/textblock.py
burdoc/elements/textlist.py
burdoc/processors/__init__.py
burdoc/processors/aggregator_processor.py
burdoc/processors/heading_processor.py
burdoc/processors/json_out_processor.py
burdoc/processors/layout_processor.py
burdoc/processors/list_processor.py
burdoc/processors/margin_processor.py
burdoc/processors/processor.py
burdoc/processors/reading_order_processor.py
burdoc/processors/pdf_load_processor/__init__.py
burdoc/processors/pdf_load_processor/drawing_handler.py
burdoc/processors/pdf_load_processor/image_handler.py
burdoc/processors/pdf_load_processor/pdf_load_processor.py
burdoc/processors/pdf_load_processor/text_handler.py
burdoc/processors/table_processors/__init__.py
burdoc/processors/table_processors/detr_table_strategy.py
burdoc/processors/table_processors/ml_table_processor.py
burdoc/processors/table_processors/rules_table_processor.py
burdoc/processors/table_processors/table_extractor_strategy.py
burdoc/scripts/__init__.py
burdoc/scripts/burdoc.py
burdoc/utils/__init__.py
burdoc/utils/compare.py
burdoc/utils/image_manip.py
burdoc/utils/json_to_html.py
burdoc/utils/layout_graph.py
burdoc/utils/logging.py
burdoc/utils/regexes.py
burdoc/utils/render_pages.py
burdoc-0.2.3.dist-info/LICENSE
burdoc-0.2.3.dist-info/METADATA
burdoc-0.2.3.dist-info/WHEEL
burdoc-0.2.3.dist-info/entry_points.txt
burdoc-0.2.3.dist-info/top_level.txt
burdoc-0.2.3.dist-info/RECORD
