Metadata-Version: 2.1
Name: burdoc
Version: 0.2.3
Summary: Advanced PDF parsing for python
Author: jennis0
Project-URL: Homepage, https://github.com/jennis0/burdoc
Project-URL: Bug Tracker, https://github.com/jennis0/burdoc/issues
Classifier: Programming Language :: Python :: 3.8
Classifier: Programming Language :: Python :: 3.9
Classifier: Programming Language :: Python :: 3.10
Classifier: Programming Language :: Python :: 3.11
Classifier: License :: OSI Approved :: MIT License
Classifier: Operating System :: OS Independent
Classifier: Topic :: Text Processing :: General
Classifier: Topic :: Text Processing :: Markup :: HTML
Requires-Python: >=3.8
License-File: LICENSE
Requires-Dist: logger-tt >=1.7
Requires-Dist: numpy >=1.24
Requires-Dist: Pillow >=9.4
Requires-Dist: plotly >=5.12
Requires-Dist: PyMuPDF >=1.21
Requires-Dist: scipy >=1.10
Requires-Dist: pandas >=1.5
Requires-Dist: torchvision >=0.14
Requires-Dist: transformers >=4.26
Requires-Dist: timm >=0.6.13
Requires-Dist: roman >=4.0
Provides-Extra: dev
Requires-Dist: pytest >=7.2.2 ; extra == 'dev'
Requires-Dist: pylint >=2.17 ; extra == 'dev'
Requires-Dist: pytest-cov >=4.0 ; extra == 'dev'
Requires-Dist: mypy ; extra == 'dev'
Requires-Dist: pylint-pytest ; extra == 'dev'
Requires-Dist: sphinx ==6.1.3 ; extra == 'dev'
Requires-Dist: sphinx-rtd-theme ; extra == 'dev'
Requires-Dist: enum-tools[sphinx] ; extra == 'dev'
Requires-Dist: myst-parser ; extra == 'dev'
Requires-Dist: yattag ; extra == 'dev'
Requires-Dist: build ; extra == 'dev'
Requires-Dist: twine ; extra == 'dev'
